06-counter/counter/counter.srcs/sources_1/new/cnt_up_down.vhd
----------------------------------------------------------
--
--! @title N-bit Up/Down binary counter
--! @author Tomas Fryza
--! Dept. of Radio Electronics, Brno Univ. of Technology, Czechia
--!
--! @copyright (c) 2019 Tomas Fryza
--! This work is licensed under the terms of the MIT license
--!
--! Implementation of bidirectional N-bit counter. Number
--! of bits is set by `g_CNT_WIDTH` and counting direction
--! by `cnt_up` input.
--
-- Hardware: Nexys A7-50T, xc7a50ticsg324-1L
-- Software: TerosHDL, Vivado 2020.2, EDA Playground
--
----------------------------------------------------------

library ieee;
  use ieee.std_logic_1164.all;
  use ieee.numeric_std.all;

----------------------------------------------------------
-- Entity declaration for N-bit counter
----------------------------------------------------------

entity cnt_up_down is
  generic (
    g_CNT_WIDTH : natural := 4 --! Default number of counter bits
  );
  port (
    clk    : in    std_logic; --! Main clock
    rst    : in    std_logic; --! Synchronous reset
    en     : in    std_logic; --! Enable input
    cnt_up : in    std_logic; --! Direction of the counter
    cnt    : out   std_logic_vector(g_CNT_WIDTH - 1 downto 0)
  );
end entity cnt_up_down;

----------------------------------------------------------
-- Architecture body for N-bit counter
----------------------------------------------------------

architecture behavioral of cnt_up_down is

  signal sig_cnt : unsigned(g_CNT_WIDTH - 1 downto 0); --! Local counter

begin

  --------------------------------------------------------
  -- p_cnt_up_down:
  -- Clocked process with synchronous reset which implements
  -- n-bit up/down counter.
  --------------------------------------------------------
  p_cnt_up_down : process (clk) is
  begin
    if rising_edge(clk) then
      if (rst = '1') then           -- Synchronous reset
        sig_cnt <= (others => '0'); -- Clear all bits
      elsif (en = '1') then         -- Test if counter is enabled
          if (cnt_up = '1') then
            sig_cnt <= sig_cnt + 1;
          else
            sig_cnt <= sig_cnt - 1;
          end if;
      end if;
    end if;
  end process p_cnt_up_down;

  -- Output must be retyped from "unsigned" to "std_logic_vector"
  cnt <= std_logic_vector(sig_cnt);

end architecture behavioral;

06-counter/counter/counter.srcs/sim_1/new/tb_cnt_up_down.vhd
----------------------------------------------------------
--
-- Testbench for N-bit Up/Down binary counter.
-- Nexys A7-50T, xc7a50ticsg324-1L
-- TerosHDL, Vivado v2020.2, EDA Playground
--
-- Copyright (c) 2020 Tomas Fryza
-- Dept. of Radio Electronics, Brno Univ. of Technology, Czechia
-- This work is licensed under the terms of the MIT license.
--
----------------------------------------------------------

library ieee;
  use ieee.std_logic_1164.all;

------------------------------------------------------------
-- Entity declaration for testbench
------------------------------------------------------------

entity tb_cnt_up_down is
  -- Entity of testbench is always empty
end entity tb_cnt_up_down;

------------------------------------------------------------
-- Architecture body for testbench
------------------------------------------------------------

architecture testbench of tb_cnt_up_down is

  -- Number of bits for testbench counter
  constant c_CNT_WIDTH         : natural := 5;
  constant c_CLK_100MHZ_PERIOD : time    := 10 ns;

  -- Local signals
  signal sig_clk_100mhz : std_logic;
  signal sig_rst        : std_logic;
  signal sig_en         : std_logic;
  signal sig_cnt_up     : std_logic;
  signal sig_cnt        : std_logic_vector(c_CNT_WIDTH - 1 downto 0);

begin

  -- Connecting testbench signals with cnt_up_down entity
  -- (Unit Under Test)
  uut_cnt : entity work.cnt_up_down
    generic map (
      g_CNT_WIDTH => c_CNT_WIDTH
    )
    port map (
      clk    => sig_clk_100mhz,
      rst    => sig_rst,
      en     => sig_en,
      cnt_up => sig_cnt_up,
      cnt    => sig_cnt
    );

  --------------------------------------------------------
  -- Clock generation process
  --------------------------------------------------------
  p_clk_gen : process is
  begin

    while now < 750 ns loop             -- 75 periods of 100MHz clock

      sig_clk_100mhz <= '0';
      wait for c_CLK_100MHZ_PERIOD / 2;
      sig_clk_100mhz <= '1';
      wait for c_CLK_100MHZ_PERIOD / 2;

    end loop;
    wait;                               -- Process is suspended forever
  end process p_clk_gen;

  --------------------------------------------------------
  -- Reset generation process
  --------------------------------------------------------
  p_reset_gen : process is
  begin

    sig_rst <= '0';
    wait for 12 ns;

    -- Reset activated
    sig_rst <= '1';
    wait for 73 ns;

    -- Reset deactivated
    sig_rst <= '0';

    wait;

  end process p_reset_gen;

  --------------------------------------------------------
  -- Data generation process
  --------------------------------------------------------
  p_stimulus : process is
  begin

    report "Stimulus process started";

    -- Enable counting
    sig_en <= '1';

    -- Change counter direction
    sig_cnt_up <= '1';
    wait for 380 ns;
    sig_cnt_up <= '0';
    wait for 186 ns;

    -- Disable counting
    sig_en <= '0';

    report "Stimulus process finished";
    wait;

  end process p_stimulus;

end architecture testbench;

06-counter/waveform.vcd
$date
  Thu Mar 16 16:21:25 2023
$end
$version
  GHDL v0
$end
$timescale
  1 fs
$end
$scope module standard $end
$upscope $end
$scope module std_logic_1164 $end
$upscope $end
$scope module numeric_std $end
$upscope $end
$scope module tb_cnt_up_down $end
$var reg 1 ! sig_clk_100mhz $end
$var reg 1 " sig_rst $end
$var reg 1 # sig_en $end
$var reg 1 $ sig_cnt_up $end
$var reg 5 % sig_cnt[4:0] $end
$scope module uut_cnt $end
$var reg 1 & clk $end
$var reg 1 ' rst $end
$var reg 1 ( en $end
$var reg 1 ) cnt_up $end
$var reg 5 * cnt[4:0] $end
$var reg 5 + sig_cnt[4:0] $end
$upscope $end
$upscope $end
$enddefinitions $end
#0
0!
0"
1#
1$
bUUUUU %
0&
0'
1(
1)
bUUUUU *
bUUUUU +
#5000000
1!
bXXXXX %
1&
bXXXXX *
bXXXXX +
#10000000
0!
0&
#12000000
1"
1'
#15000000
1!
b00000 %
1&
b00000 *
b00000 +
#20000000
0!
0&
#25000000
1!
1&
#30000000
0!
0&
#35000000
1!
1&
#40000000
0!
0&
#45000000
1!
1&
#50000000
0!
0&
#55000000
1!
1&
#60000000
0!
0&
#65000000
1!
1&
#70000000
0!
0&
#75000000
1!
1&
#80000000
0!
0&
#85000000
1!
0"
b00001 %
1&
0'
b00001 *
b00001 +
#90000000
0!
0&
#95000000
1!
b00010 %
1&
b00010 *
b00010 +
#100000000
0!
0&
#105000000
1!
b00011 %
1&
b00011 *
b00011 +
#110000000
0!
0&
#115000000
1!
b00100 %
1&
b00100 *
b00100 +
#120000000
0!
0&
#125000000
1!
b00101 %
1&
b00101 *
b00101 +
#130000000
0!
0&
#135000000
1!
b00110 %
1&
b00110 *
b00110 +
#140000000
0!
0&
#145000000
1!
b00111 %
1&
b00111 *
b00111 +
#150000000
0!
0&
#155000000
1!
b01000 %
1&
b01000 *
b01000 +
#160000000
0!
0&
#165000000
1!
b01001 %
1&
b01001 *
b01001 +
#170000000
0!
0&
#175000000
1!
b01010 %
1&
b01010 *
b01010 +
#180000000
0!
0&
#185000000
1!
b01011 %
1&
b01011 *
b01011 +
#190000000
0!
0&
#195000000
1!
b01100 %
1&
b01100 *
b01100 +
#200000000
0!
0&
#205000000
1!
b01101 %
1&
b01101 *
b01101 +
#210000000
0!
0&
#215000000
1!
b01110 %
1&
b01110 *
b01110 +
#220000000
0!
0&
#225000000
1!
b01111 %
1&
b01111 *
b01111 +
#230000000
0!
0&
#235000000
1!
b10000 %
1&
b10000 *
b10000 +
#240000000
0!
0&
#245000000
1!
b10001 %
1&
b10001 *
b10001 +
#250000000
0!
0&
#255000000
1!
b10010 %
1&
b10010 *
b10010 +
#260000000
0!
0&
#265000000
1!
b10011 %
1&
b10011 *
b10011 +
#270000000
0!
0&
#275000000
1!
b10100 %
1&
b10100 *
b10100 +
#280000000
0!
0&
#285000000
1!
b10101 %
1&
b10101 *
b10101 +
#290000000
0!
0&
#295000000
1!
b10110 %
1&
b10110 *
b10110 +
#300000000
0!
0&
#305000000
1!
b10111 %
1&
b10111 *
b10111 +
#310000000
0!
0&
#315000000
1!
b11000 %
1&
b11000 *
b11000 +
#320000000
0!
0&
#325000000
1!
b11001 %
1&
b11001 *
b11001 +
#330000000
0!
0&
#335000000
1!
b11010 %
1&
b11010 *
b11010 +
#340000000
0!
0&
#345000000
1!
b11011 %
1&
b11011 *
b11011 +
#350000000
0!
0&
#355000000
1!
b11100 %
1&
b11100 *
b11100 +
#360000000
0!
0&
#365000000
1!
b11101 %
1&
b11101 *
b11101 +
#370000000
0!
0&
#375000000
1!
b11110 %
1&
b11110 *
b11110 +
#380000000
0!
0$
0&
0)
#385000000
1!
b11101 %
1&
b11101 *
b11101 +
#390000000
0!
0&
#395000000
1!
b11100 %
1&
b11100 *
b11100 +
#400000000
0!
0&
#405000000
1!
b11011 %
1&
b11011 *
b11011 +
#410000000
0!
0&
#415000000
1!
b11010 %
1&
b11010 *
b11010 +
#420000000
0!
0&
#425000000
1!
b11001 %
1&
b11001 *
b11001 +
#430000000
0!
0&
#435000000
1!
b11000 %
1&
b11000 *
b11000 +
#440000000
0!
0&
#445000000
1!
b10111 %
1&
b10111 *
b10111 +
#450000000
0!
0&
#455000000
1!
b10110 %
1&
b10110 *
b10110 +
#460000000
0!
0&
#465000000
1!
b10101 %
1&
b10101 *
b10101 +
#470000000
0!
0&
#475000000
1!
b10100 %
1&
b10100 *
b10100 +
#480000000
0!
0&
#485000000
1!
b10011 %
1&
b10011 *
b10011 +
#490000000
0!
0&
#495000000
1!
b10010 %
1&
b10010 *
b10010 +
#500000000
0!
0&
#505000000
1!
b10001 %
1&
b10001 *
b10001 +
#510000000
0!
0&
#515000000
1!
b10000 %
1&
b10000 *
b10000 +
#520000000
0!
0&
#525000000
1!
b01111 %
1&
b01111 *
b01111 +
#530000000
0!
0&
#535000000
1!
b01110 %
1&
b01110 *
b01110 +
#540000000
0!
0&
#545000000
1!
b01101 %
1&
b01101 *
b01101 +
#550000000
0!
0&
#555000000
1!
b01100 %
1&
b01100 *
b01100 +
#560000000
0!
0&
#565000000
1!
b01011 %
1&
b01011 *
b01011 +
#566000000
0#
0(
